easysemver/__init__.py
easysemver/main.py
easysemver-0.2.0.dist-info/LICENSE
easysemver-0.2.0.dist-info/METADATA
easysemver-0.2.0.dist-info/WHEEL
easysemver-0.2.0.dist-info/top_level.txt
easysemver-0.2.0.dist-info/RECORD
