Metadata-Version: 2.1
Name: easysemver
Version: 0.2.0
Summary: Simple semver utilities for Python.
Home-page: https://github.com/azimuth-cloud/easysemver
Author: Matt Pryor
Author-email: matt@stackhpc.com
License-File: LICENSE
